{"generated_at": "2026-07-22 04:34:59", "districts": {"10": [["Purba Champaran", 9820], ["Vaishali", 7531], ["Kishanganj", 6836], ["Saran", 6210], ["Purnia", 6189], ["Gaya", 5626], ["Madhubani", 5293], ["Begusarai", 5128], ["Muzaffarpur", 5083], ["Patna", 4467], ["Darbhanga", 4173], ["Katihar", 3895], ["Araria", 3719], ["Madhepura", 3682], ["Sitamarhi", 3621], ["Rohtas", 2666], ["Bhagalpur", 2585], ["Saharsa", 2424], ["Gopalganj", 2332], ["Bhojpur", 2284], ["Jamui", 2278], ["Arwal", 2256], ["Supaul", 2046], ["Pashchim Champaran", 1860], ["Nawada", 1734], ["Aurangabad", 1446], ["Siwan", 1359], ["Samastipur", 915], ["Lakhisarai", 795], ["Sheohar", 694], ["Khagaria", 674], ["Munger", 602], ["Banka", 512], ["Jehanabad", 469], ["Sheikhpura", 457], ["Nalanda", 377], ["Buxar", 372], ["Kaimur Bhabua", 151]], "11": [["South District", 16], ["North District", 11], ["East District", 8], ["West District", 1]], "12": [["East Kameng", 104], ["Papum Pare", 97], ["Lower Subansiri", 68], ["Kurung Kumey", 50], ["Kamle", 49], ["Upper Subansiri", 32], ["Changlang", 31], ["Kra Daadi", 30], ["Longding", 12], ["Namsai", 12], ["West Siang", 10], ["Upper Siang", 9], ["Tirap", 6], ["Leparada", 4], ["West Kameng", 3], ["Siang", 2], ["Tawang", 1], ["Dibang Valley", 1], ["Anjaw", 1]], "13": [["Wokha", 321], ["Mokokchung", 225], ["Tuensang", 223], ["Dimapur", 205], ["Kohima", 190], ["Peren", 102], ["Phek", 87], ["Zunheboto", 77], ["Mon", 50], ["Kiphire", 9], ["Longleng", 7]], "14": [["Imphal East", 9606], ["Imphal West", 7706], ["Thoubal", 4278], ["Bishnupur", 4218], ["Kakching", 1873], ["Jiribam", 144]], "15": [["Serchhip", 1428], ["Aizawl", 1283], ["Champhai", 949], ["Kolasib", 686], ["Lunglei", 565], ["Lawngtlai", 404], ["Mamit", 286], ["Saiha", 100]], "16": [["West Tripura", 4382], ["Sepahijala", 455], ["Gomti", 321], ["Khowai", 319], ["South Tripura", 267], ["Dhalai", 249], ["North Tripura", 220], ["Unokoti", 127]], "17": [["West Khasi Hills", 414], ["Ri Bhoi", 298], ["West Garo Hills", 262], ["East Garo Hills", 221], ["South Garo Hills", 168], ["Jaintia Hills", 46], ["East Khasi Hills", 41]], "18": [["Sonitpur", 4714], ["Dibrugarh", 2403], ["Dhubri", 2364], ["Karimganj", 1797], ["Karbi Anglong", 1670], ["Dhemaji", 1641], ["Golaghat", 1548], ["Nagaon", 1447], ["Cachar", 1392], ["Jorhat", 1206], ["Lakhimpur", 861], ["Dima Hasao", 855], ["Kokrajhar", 824], ["Morigaon", 816], ["Barpeta", 653], ["Goalpara", 581], ["Tinsukia", 554], ["Darrang", 552], ["Tamulpur", 540], ["Nalbari", 519], ["Biswanath", 463], ["Bongaigaon", 433], ["Kamrup", 429], ["Bajali", 419], ["Hojai", 412], ["Charaideo", 384], ["Chirang", 371], ["Sivasagar", 354], ["Hailakandi", 340], ["Kamrup Metropolitan", 305], ["Udalguri", 239], ["West Karbi Anglong", 207]], "19": [["North 24 Parganas", 27618], ["Murshidabad", 13288], ["Jalpaiguri", 11884], ["Uttar Dinajpur", 9215], ["Hooghly", 7416], ["Paschim Bardhaman", 7297], ["Darjiling", 7251], ["South 24 Parganas", 6603], ["Nadia", 6393], ["Birbhum", 6282], ["Purulia", 5945], ["Purba Medinipur", 5305], ["Cooch Behar", 5205], ["Paschim Medinipur", 4863], ["Dakshin Dinajpur", 3673], ["Purba Bardhaman", 3161], ["Alipurduar", 2350], ["Maldah", 1717], ["Howrah", 788], ["Bankura", 787], ["Kolkata", 736], ["Kalimpong", 628], ["Jhargram", 210]], "1": [["Baramula", 3191], ["Anantnag", 2091], ["Jammu", 1814], ["Bandipore", 1333], ["Badgam", 917], ["Kupwara", 877], ["Srinagar", 876], ["Rajouri", 722], ["Doda", 699], ["Kathua", 567], ["Kulgam", 445], ["Udhampur", 407], ["Pulwama", 340], ["Reasi", 271], ["Punch", 262], ["Samba", 189], ["Ramban", 183], ["Ganderbal", 160], ["Shupiyan", 126], ["Kishtwar", 48]], "20": [["Palamu", 6361], ["Deoghar", 3950], ["Giridih", 3853], ["Garhwa", 3588], ["Ranchi", 2512], ["Hazaribagh", 2408], ["Godda", 2357], ["Dumka", 1957], ["Gumla", 1823], ["Dhanbad", 1785], ["Sahibganj", 1701], ["Khunti", 1341], ["Simdega", 1310], ["East Singhbhum", 1212], ["Jamtara", 1192], ["Kodarma", 1179], ["Bokaro", 1071], ["Lohardaga", 1050], ["Ramgarh", 989], ["Chatra", 774], ["Latehar", 678], ["Pashchimi Singhbhum", 664], ["Pakur", 572], ["Saraikela Kharsawan", 104]], "21": [["Koraput", 2983], ["Nuapada", 1525], ["Kendujhar", 1521], ["Mayurbhanj", 1154], ["Bhadrak", 1088], ["Sambalpur", 1044], ["Dhenkanal", 1033], ["Sundargarh", 1020], ["Ganjam", 1006], ["Cuttack", 961], ["Kalahandi", 924], ["Khordha", 855], ["Balasore", 780], ["Balangir", 766], ["Kandhamal", 715], ["Anugul", 652], ["Puri", 617], ["Jharsuguda", 609], ["Subarnapur", 582], ["Rayagada", 515], ["Kendrapara", 487], ["Malkangiri", 484], ["Bargarh", 360], ["Nayagarh", 353], ["Nabarangapur", 300], ["Debagarh", 200], ["Jajapur", 198], ["Jagatsinghapur", 145], ["Baudh", 113], ["Gajapati", 75]], "22": [["Bilaspur", 4922], ["Raipur", 4212], ["Durg", 3472], ["Surguja", 2514], ["Rajnandgaon", 1852], ["Janjgir Champa", 1784], ["Raigarh", 1762], ["Kabeerdham", 1494], ["Jashpur", 1443], ["Mahasamund", 1388], ["Dhamtari", 973], ["Bastar", 812], ["Korba", 779], ["Uttar Bastar Kanker", 653], ["Dakshin Bastar Dantewada", 545], ["Mungeli", 425], ["Kondagaon", 307], ["Koriya", 305], ["Surajpur", 241], ["Bijapur", 150], ["Gariyaband", 105], ["Sukma", 87], ["Balod", 87], ["Bemetara", 69], ["Balodabazar", 66], ["Narayanpur", 46], ["Balrampur", 41]], "23": [["Sagar", 4648], ["Chhindwara", 3981], ["Ujjain", 2891], ["Damoh", 2869], ["Tikamgarh", 2584], ["Dhar", 2309], ["Panna", 2088], ["Dewas", 2070], ["Chhatarpur", 2052], ["Jabalpur", 2022], ["Satna", 2001], ["Burhanpur", 1783], ["Khargone", 1723], ["Rewa", 1658], ["Ratlam", 1630], ["Vidisha", 1628], ["Guna", 1628], ["Narsimhapur", 1609], ["Sehore", 1601], ["Hoshangabad", 1590], ["Rajgarh", 1509], ["Raisen", 1475], ["Shahdol", 1388], ["Bhind", 1350], ["Balaghat", 1189], ["Mandsaur", 1186], ["Sidhi", 1173], ["Datia", 1133], ["Sheopur", 1100], ["Shivpuri", 1024], ["Shajapur", 1012], ["Mandla", 999], ["Ashoknagar", 981], ["Gwalior", 980], ["Anuppur", 892], ["Neemuch", 872], ["Barwani", 839], ["East Nimar", 839], ["Harda", 647], ["Singrauli", 630], ["Jhabua", 583], ["Morena", 530], ["Umaria", 511], ["Betul", 511], ["Seoni", 438], ["Indore", 399], ["Katni", 361], ["Bhopal", 227], ["Dindori", 189], ["Alirajpur", 163]], "24": [["Ahmedabad", 2097], ["Surendranagar", 752], ["Gandhinagar", 686], ["Bhavnagar", 669], ["Banas Kantha", 638], ["Junagadh", 514], ["Amreli", 495], ["Kheda", 479], ["Patan", 434], ["Jamnagar", 429], ["Vadodara", 389], ["Rajkot", 377], ["Mahesana", 359], ["Surat", 288], ["Anand", 245], ["Sabar Kantha", 226], ["Panch Mahals", 223], ["Porbandar", 211], ["Kachchh", 159], ["Valsad", 108], ["Dohad", 67], ["Bharuch", 66], ["Navsari", 46], ["Narmada", 30], ["Tapi", 19]], "27": [["Parbhani", 10268], ["Nanded", 7502], ["Nagpur", 5483], ["Yavatmal", 4931], ["Amravati", 4696], ["Akola", 4606], ["Jalna", 4039], ["Bid", 3828], ["Hingoli", 3073], ["Aurangabad", 2779], ["Latur", 2459], ["Pune", 2157], ["Solapur", 2149], ["Gondiya", 2121], ["Buldana", 2015], ["Ahmadnagar", 1956], ["Sangli", 1775], ["Osmanabad", 1548], ["Jalgaon", 1495], ["Wardha", 1328], ["Chandrapur", 1039], ["Nashik", 789], ["Bhandara", 765], ["Gadchiroli", 728], ["Satara", 654], ["Dhule", 621], ["Washim", 531], ["Kolhapur", 527], ["Nandurbar", 508], ["Raigarh", 424], ["Palghar", 34], ["Ratnagiri", 13], ["Sindhudurg", 8], ["Thane", 2]], "28": [["Krishna", 113037], ["Visakhapatnam", 109045], ["Ysr Kadapa", 81024], ["West Godavari", 79045], ["East Godavari", 73959], ["Guntur", 70039], ["Ananthapur", 68405], ["Chittoor", 67951], ["Sri Potti Sriramulu Nellore", 67545], ["Kurnool", 57208], ["Srikakulam", 49476], ["Vizianagaram", 47746], ["Prakasam", 45153], ["Ntr", 31163], ["Tirupati", 27974], ["Kakinada", 26822], ["Eluru", 19372], ["Sri Sathya Sai", 19325], ["Palnadu", 18927], ["Nandyal", 10809], ["Annamayya", 10637], ["Parvathipuram Manyam", 7057], ["Bapatla", 5475], ["Konaseema", 4410], ["Anakapalli", 3622]], "29": [["Belgaum", 6232], ["Raichur", 4681], ["Bijapur", 4345], ["Mysore", 4107], ["Bagalkot", 4061], ["Gulbarga", 3937], ["Dharwad", 3719], ["Gadag", 3457], ["Koppal", 2895], ["Bellary", 2827], ["Chitradurga", 2614], ["Vijaynagar", 2564], ["Yadgir", 2380], ["Davanagere", 2200], ["Shimoga", 2010], ["Bidar", 1937], ["Uttara Kannada", 1856], ["Ramanagara", 1751], ["Hassan", 1708], ["Haveri", 1683], ["Tumkur", 1529], ["Chikkaballapura", 1325], ["Kolar", 1291], ["Dakshina Kannada", 1229], ["Bangalore Rural", 955], ["Mandya", 872], ["Bangalore", 866], ["Chamarajanagar", 730], ["Udupi", 696], ["Kodagu", 392], ["Chikmagalur", 351]], "2": [["Kangra", 1160], ["Mandi", 415], ["Una", 197], ["Sirmaur", 148], ["Kullu", 142], ["Shimla", 96], ["Chamba", 76], ["Bilaspur", 71], ["Hamirpur", 55], ["Solan", 53]], "30": [["North Goa", 1]], "32": [["Thiruvananthapuram", 3590], ["Kollam", 2598], ["Malappuram", 2166], ["Palakkad", 1908], ["Ernakulam", 1796], ["Kozhikode", 1508], ["Alappuzha", 1171], ["Thrissur", 1162], ["Wayanad", 1151], ["Kottayam", 709], ["Pathanamthitta", 675], ["Kasaragod", 646], ["Kannur", 587], ["Idukki", 271]], "33": [["Chennai", 16747], ["Vellore", 3670], ["Tirunelveli", 3488], ["Salem", 3074], ["Tiruchirappalli", 2756], ["Kancheepuram", 2348], ["Kanniyakumari", 2125], ["Thiruvallur", 1933], ["Cuddalore", 1854], ["Madurai", 1664], ["Erode", 1622], ["Thanjavur", 1570], ["Viluppuram", 1519], ["Coimbatore", 1436], ["Dindigul", 1361], ["Namakkal", 1351], ["Nilgiris", 1336], ["Tiruppur", 1208], ["Tiruvannamalai", 1043], ["Thoothukkudi", 880], ["Nagapattinam", 872], ["Thiruvarur", 866], ["Pudukkottai", 811], ["Dharmapuri", 768], ["Theni", 660], ["Ramanathapuram", 629], ["Karur", 609], ["Krishnagiri", 557], ["Virudhunagar", 387], ["Perambalur", 358], ["Mayiladuthurai", 277], ["Ariyalur", 264], ["Sivaganga", 175]], "34": [["Puducherry", 4491], ["Karaikal", 1319], ["Yanam", 175], ["Mahe", 94]], "35": [["South Andaman", 4]], "37": [["Kargil", 58]], "3": [["Jalandhar", 4134], ["Amristar", 2868], ["Ludhiana", 2688], ["Patiala", 2280], ["Bathinda", 2209], ["Mansa", 1641], ["Gurdaspur", 1627], ["Barnala", 1406], ["Pathankot", 1310], ["Mukstar", 1249], ["Firozpur", 1085], ["Tarn Taran", 1060], ["Fazalika", 1013], ["Moga", 1010], ["Sangrur", 957], ["Sahibzada Ajit Singh Nagar", 807], ["Faridkot", 738], ["Hoshiarpur", 623], ["Malerkotla", 535], ["Kapurthala", 500], ["Fathegarh Sahib", 428], ["Shahid Bhagat Singh Nagar", 405], ["Rupnagar", 205]], "5": [["Hardwar", 3350], ["Garhwal", 942], ["Udham Singh Nagar", 926], ["Nainital", 305], ["Chamoli", 289], ["Dehradun", 237], ["Pithoragarh", 220], ["Uttarkashi", 185], ["Bageshwar", 159], ["Almora", 63], ["Tehri Garhwal", 43], ["Rudraprayag", 35], ["Champawat", 17]], "6": [["Fatehabad", 1639], ["Yamunanagar", 1545], ["Hisar", 1384], ["Ambala", 1301], ["Jind", 1287], ["Palwal", 1189], ["Mahendragarh", 1143], ["Kaithal", 1111], ["Sonipat", 893], ["Mewat", 793], ["Bhiwani", 701], ["Rohtak", 535], ["Panipat", 453], ["Gurugram", 322], ["Jhajjar", 251], ["Karnal", 245], ["Kurukshetra", 218], ["Sirsa", 155], ["Faridabad", 129], ["Charkhidadri", 129], ["Rewari", 83]], "8": [["Jodhpur", 5302], ["Jalor", 1220], ["Karauli", 1167], ["Ajmer", 949], ["Jaipur Gramin", 946], ["Bikaner", 899], ["Dhaulpur", 883], ["Udaipur", 778], ["Pali", 772], ["Hanumangarh", 705], ["Dausa", 695], ["Baran", 674], ["Bhilwara", 657], ["Sirohi", 639], ["Sawai Madhopur", 630], ["Ganganagar", 609], ["Kota", 608], ["Chittaurgarh", 577], ["Tonk", 575], ["Jaipur", 538], ["Jhunjhunun", 481], ["Bundi", 459], ["Sikar", 448], ["Dudu", 433], ["Churu", 365], ["Barmer", 349], ["Jodhpur Gramin", 303], ["Banswara", 291], ["Bharatpur", 288], ["Nagaur", 286], ["Jaisalmer", 193], ["Dungarpur", 190], ["Rajasmand", 154], ["Alwar", 143], ["Jhalawar", 142], ["Pratapgarh", 126], ["Sanchor", 33], ["Gangapurcity", 32], ["Khairthal Tijara", 16], ["Didwana Kuchaman", 4], ["Kotputli Behror", 3], ["Balotra", 2]], "9": [["Mirzapur", 3525], ["Firozabad", 3347], ["Bulandshahr", 2767], ["Gorakhpur", 2246], ["Bijnor", 2088], ["Jaunpur", 2044], ["Lakhimpur Kheri", 2019], ["Mathura", 1932], ["Ghaziabad", 1928], ["Prayagraj", 1764], ["Lucknow", 1707], ["Meerut", 1681], ["Muzzaffarnagar", 1676], ["Shahjahanpur", 1538], ["Lalitpur", 1400], ["Pilibhit", 1386], ["Mahoba", 1383], ["Kushinagar", 1335], ["Deoria", 1328], ["Sitapur", 1305], ["Aligarh", 1275], ["Ballia", 1254], ["Moradabad", 1175], ["Saharanpur", 1106], ["Ambedkar Nagar", 1095], ["Mau", 1079], ["Jhansi", 1020], ["Shamli", 1009], ["Varanasi", 1003], ["Bara Banki", 993], ["Bhadohi", 972], ["Bareilly", 951], ["Ghazipur", 922], ["Agra", 917], ["Rampur", 912], ["Ayodhya", 885], ["Maharajganj", 884], ["Etawah", 841], ["Sant Kabir Nagar", 828], ["Unnao", 821], ["Bahraich", 800], ["Hardoi", 769], ["Siddharthnagar", 768], ["Hapur", 765], ["Sonbhadra", 762], ["Basti", 744], ["Baghpat", 743], ["Budaun", 734], ["Balrampur", 709], ["Pratapgarh", 629], ["Rae Bareli", 628], ["Fatehpur", 626], ["Banda", 594], ["Hathras", 589], ["Jalaun", 584], ["Kaushambi", 555], ["Kanpur Dehat", 551], ["Azamgarh", 530], ["Mainpuri", 528], ["Etah", 524], ["Kasganj", 507], ["Sambhal", 493], ["Chitrakoot", 457], ["Amroha", 452], ["Kannauj", 450], ["Amethi", 409], ["Chandauli", 407], ["Farrukhabad", 385], ["Auraiya", 353], ["Kanpur Nagar", 301], ["Shrawasti", 277], ["Gonda", 257], ["Hamirpur", 253], ["Gautam Buddha Nagar", 96], ["Sultanpur", 91]]}}